lookit/__init__.py
lookit/cli.py
lookit/tools/__init__.py
lookit/tools/computer_use.py
lookit/tools/mobile_use.py
lookit/utils/__init__.py
lookit/utils/image.py
lookit/utils/visualization.py
lookit-0.1.1.dist-info/licenses/LICENSE
lookit-0.1.1.dist-info/METADATA
lookit-0.1.1.dist-info/WHEEL
lookit-0.1.1.dist-info/entry_points.txt
lookit-0.1.1.dist-info/top_level.txt
lookit-0.1.1.dist-info/RECORD
