Metadata-Version: 2.4
Name: lookit
Version: 0.1.1
Summary: LLM-first vision toolkit for GUI grounding, OCR, and more
License-Expression: MIT
Project-URL: Homepage, https://github.com/atom2ueki/lookit
Project-URL: Repository, https://github.com/atom2ueki/lookit
Requires-Python: <4.0,>=3.11
License-File: LICENSE
Requires-Dist: langchain-core<2.0.0,>=1.1.0
Requires-Dist: langchain-openai<2.0.0,>=1.0.0
Requires-Dist: pydantic<3.0.0,>=2.7.4
Requires-Dist: pillow>=10.0.0
Requires-Dist: python-dotenv>=1.0.0
Dynamic: license-file
